[{"active":0,"id":1,"name":"name","code":"alpha-2"},{"active":0,"id":25,"name":"Afghanistan","code":"AF"},{"active":0,"id":1,"name":"\u00c5land Islands","code":"AX"},{"active":0,"id":92,"name":"Albania","code":"AL"},{"active":0,"id":52,"name":"Algeria","code":"DZ"},{"active":0,"id":1,"name":"American Samoa","code":"AS"},{"active":0,"id":1,"name":"Andorra","code":"AD"},{"active":0,"id":51,"name":"Angola","code":"AO"},{"active":0,"id":1,"name":"Anguilla","code":"AI"},{"active":0,"id":1,"name":"Antarctica","code":"AQ"},{"active":0,"id":1,"name":"Antigua and Barbuda","code":"AG"},{"active":0,"id":110,"name":"Argentina","code":"AR"},{"active":1,"id":118,"name":"Armenia","code":"AM"},{"active":0,"id":1,"name":"Aruba","code":"AW"},{"active":0,"id":11,"name":"Australia","code":"AU"},{"active":0,"id":16,"name":"Austria","code":"AT"},{"active":0,"id":125,"name":"Azerbaijan","code":"AZ"},{"active":0,"id":114,"name":"Bahamas","code":"BS"},{"active":0,"id":95,"name":"Bahrain","code":"BH"},{"active":0,"id":150,"name":"Bangladesh","code":"BD"},{"active":0,"id":134,"name":"Barbados","code":"BB"},{"active":0,"id":35,"name":"Belarus","code":"BY"},{"active":0,"id":8,"name":"Belgium","code":"BE"},{"active":0,"id":1,"name":"Belize","code":"BZ"},{"active":0,"id":1,"name":"Benin","code":"BJ"},{"active":0,"id":1,"name":"Bermuda","code":"BM"},{"active":0,"id":136,"name":"Bhutan","code":"BT"},{"active":0,"id":1,"name":"Bolivia (Plurinational State of)","code":"BO"},{"active":0,"id":1,"name":"\"Bonaire","code":" Sint Eustatius and Saba\""},{"active":0,"id":137,"name":"Bosnia and Herzegovina","code":"BA"},{"active":0,"id":85,"name":"Botswana","code":"BW"},{"active":0,"id":1,"name":"Bouvet Island","code":"BV"},{"active":0,"id":4,"name":"Brazil","code":"BR"},{"active":0,"id":1,"name":"British Indian Ocean Territory","code":"IO"},{"active":0,"id":1,"name":"Brunei Darussalam","code":"BN"},{"active":0,"id":86,"name":"Bulgaria","code":"BG"},{"active":0,"id":59,"name":"Burkina Faso","code":"BF"},{"active":0,"id":108,"name":"Burundi","code":"BI"},{"active":0,"id":144,"name":"Cambodia","code":"KH"},{"active":0,"id":1,"name":"Cameroon","code":"CM"},{"active":0,"id":19,"name":"Canada","code":"CA"},{"active":0,"id":76,"name":"Cabo Verde","code":"CV"},{"active":0,"id":1,"name":"Cayman Islands","code":"KY"},{"active":0,"id":57,"name":"Central African Republic","code":"CF"},{"active":0,"id":61,"name":"Chad","code":"TD"},{"active":0,"id":97,"name":"Chile","code":"CL"},{"active":0,"id":28,"name":"China","code":"CN"},{"active":0,"id":1,"name":"Christmas Island","code":"CX"},{"active":0,"id":1,"name":"Cocos (Keeling) Islands","code":"CC"},{"active":0,"id":151,"name":"Colombia","code":"CO"},{"active":0,"id":1,"name":"Comoros","code":"KM"},{"active":0,"id":1,"name":"Congo","code":"CG"},{"active":0,"id":41,"name":"Congo (Democratic Republic of the)","code":"CD"},{"active":0,"id":1,"name":"Cook Islands","code":"CK"},{"active":0,"id":126,"name":"Costa Rica","code":"CR"},{"active":0,"id":60,"name":"C\u00f4te d'Ivoire","code":"CI"},{"active":0,"id":78,"name":"Croatia","code":"HR"},{"active":0,"id":36,"name":"Cuba","code":"CU"},{"active":0,"id":98,"name":"Cura\u00e7ao","code":"CW"},{"active":0,"id":9,"name":"Cyprus","code":"CY"},{"active":0,"id":91,"name":"Czech Republic","code":"CZ"},{"active":0,"id":10,"name":"Denmark","code":"DK"},{"active":0,"id":70,"name":"Djibouti","code":"DJ"},{"active":0,"id":1,"name":"Dominica","code":"DM"},{"active":0,"id":140,"name":"Dominican Republic","code":"DO"},{"active":0,"id":104,"name":"Ecuador","code":"EC"},{"active":0,"id":42,"name":"Egypt","code":"EG"},{"active":0,"id":127,"name":"El Salvador","code":"SV"},{"active":0,"id":141,"name":"Equatorial Guinea","code":"GQ"},{"active":0,"id":149,"name":"Eritrea","code":"ER"},{"active":1,"id":79,"name":"Estonia","code":"EE"},{"active":0,"id":68,"name":"Ethiopia","code":"ET"},{"active":0,"id":1,"name":"Falkland Islands (Malvinas)","code":"FK"},{"active":0,"id":1,"name":"Faroe Islands","code":"FO"},{"active":0,"id":1,"name":"Fiji","code":"FJ"},{"active":0,"id":26,"name":"Finland","code":"FI"},{"active":0,"id":18,"name":"France","code":"FR"},{"active":0,"id":1,"name":"French Guiana","code":"GF"},{"active":0,"id":1,"name":"French Polynesia","code":"PF"},{"active":0,"id":1,"name":"French Southern Territories","code":"TF"},{"active":0,"id":67,"name":"Gabon","code":"GA"},{"active":0,"id":139,"name":"Gambia","code":"GM"},{"active":0,"id":121,"name":"Georgia","code":"GE"},{"active":0,"id":15,"name":"Germany","code":"DE"},{"active":0,"id":69,"name":"Ghana","code":"GH"},{"active":0,"id":1,"name":"Gibraltar","code":"GI"},{"active":0,"id":5,"name":"Greece","code":"GR"},{"active":0,"id":1,"name":"Greenland","code":"GL"},{"active":0,"id":1,"name":"Grenada","code":"GD"},{"active":0,"id":1,"name":"Guadeloupe","code":"GP"},{"active":0,"id":1,"name":"Guam","code":"GU"},{"active":0,"id":1,"name":"Guatemala","code":"GT"},{"active":0,"id":1,"name":"Guernsey","code":"GG"},{"active":0,"id":66,"name":"Guinea","code":"GN"},{"active":0,"id":143,"name":"Guinea-Bissau","code":"GW"},{"active":0,"id":1,"name":"Guyana","code":"GY"},{"active":0,"id":1,"name":"Haiti","code":"HT"},{"active":0,"id":1,"name":"Heard Island and McDonald Islands","code":"HM"},{"active":0,"id":1,"name":"Holy See","code":"VA"},{"active":0,"id":1,"name":"Honduras","code":"HN"},{"active":0,"id":1,"name":"Hong Kong","code":"HK"},{"active":0,"id":17,"name":"Hungary","code":"HU"},{"active":0,"id":1,"name":"Iceland","code":"IS"},{"active":0,"id":13,"name":"India","code":"IN"},{"active":0,"id":81,"name":"Indonesia","code":"ID"},{"active":0,"id":33,"name":"Iran (Islamic Republic of)","code":"IR"},{"active":0,"id":23,"name":"Iraq","code":"IQ"},{"active":0,"id":1,"name":"Ireland","code":"IE"},{"active":0,"id":1,"name":"Isle of Man","code":"IM"},{"active":0,"id":77,"name":"Israel","code":"IL"},{"active":0,"id":82,"name":"Italy","code":"IT"},{"active":0,"id":102,"name":"Jamaica","code":"JM"},{"active":0,"id":103,"name":"Japan","code":"JP"},{"active":0,"id":1,"name":"Jersey","code":"JE"},{"active":0,"id":1,"name":"Jordan","code":"JO"},{"active":0,"id":38,"name":"Kazakhstan","code":"KZ"},{"active":0,"id":71,"name":"Kenya","code":"KE"},{"active":0,"id":1,"name":"Kiribati","code":"KI"},{"active":0,"id":88,"name":"Korea (Democratic People's Republic of)","code":"KP"},{"active":0,"id":145,"name":"Korea (Republic of)","code":"KR"},{"active":0,"id":1,"name":"Kuwait","code":"KW"},{"active":0,"id":46,"name":"Kyrgyzstan","code":"KG"},{"active":0,"id":115,"name":"Lao People's Democratic Republic","code":"LA"},{"active":0,"id":40,"name":"Latvia","code":"LV"},{"active":0,"id":147,"name":"Lebanon","code":"LB"},{"active":0,"id":84,"name":"Lesotho","code":"LS"},{"active":0,"id":55,"name":"Liberia","code":"LR"},{"active":0,"id":75,"name":"Libya","code":"LY"},{"active":0,"id":1,"name":"Liechtenstein","code":"LI"},{"active":0,"id":43,"name":"Lithuania","code":"LT"},{"active":0,"id":100,"name":"Luxembourg","code":"LU"},{"active":0,"id":1,"name":"Macao","code":"MO"},{"active":0,"id":122,"name":"Macedonia (the former Yugoslav Republic of)","code":"MK"},{"active":0,"id":73,"name":"Madagascar","code":"MG"},{"active":0,"id":72,"name":"Malawi","code":"MW"},{"active":0,"id":119,"name":"Malaysia","code":"MY"},{"active":0,"id":1,"name":"Maldives","code":"MV"},{"active":0,"id":53,"name":"Mali","code":"ML"},{"active":0,"id":1,"name":"Malta","code":"MT"},{"active":0,"id":1,"name":"Marshall Islands","code":"MH"},{"active":0,"id":1,"name":"Martinique","code":"MQ"},{"active":0,"id":138,"name":"Mauritania","code":"MR"},{"active":0,"id":131,"name":"Mauritius","code":"MU"},{"active":0,"id":1,"name":"Mayotte","code":"YT"},{"active":0,"id":83,"name":"Mexico","code":"MX"},{"active":0,"id":1,"name":"Micronesia (Federated States of)","code":"FM"},{"active":0,"id":117,"name":"Moldova (Republic of)","code":"MD"},{"active":0,"id":1,"name":"Monaco","code":"MC"},{"active":0,"id":49,"name":"Mongolia","code":"MN"},{"active":0,"id":116,"name":"Montenegro","code":"ME"},{"active":0,"id":1,"name":"Montserrat","code":"MS"},{"active":0,"id":31,"name":"Morocco","code":"MA"},{"active":0,"id":56,"name":"Mozambique","code":"MZ"},{"active":0,"id":39,"name":"Myanmar","code":"MM"},{"active":0,"id":93,"name":"Namibia","code":"NA"},{"active":0,"id":1,"name":"Nauru","code":"NR"},{"active":0,"id":80,"name":"Nepal","code":"NP"},{"active":0,"id":96,"name":"Netherlands","code":"NL"},{"active":0,"id":1,"name":"New Caledonia","code":"NC"},{"active":0,"id":3,"name":"New Zealand","code":"NZ"},{"active":0,"id":123,"name":"Nicaragua","code":"NI"},{"active":0,"id":50,"name":"Niger","code":"NE"},{"active":0,"id":64,"name":"Nigeria","code":"NG"},{"active":0,"id":1,"name":"Niue","code":"NU"},{"active":0,"id":1,"name":"Norfolk Island","code":"NF"},{"active":0,"id":1,"name":"Northern Mariana Islands","code":"MP"},{"active":0,"id":22,"name":"Norway","code":"NO"},{"active":0,"id":128,"name":"Oman","code":"OM"},{"active":0,"id":14,"name":"Pakistan","code":"PK"},{"active":0,"id":1,"name":"Palau","code":"PW"},{"active":0,"id":1,"name":"\"Palestine","code":" State of\""},{"active":0,"id":1,"name":"Panama","code":"PA"},{"active":0,"id":129,"name":"Papua New Guinea","code":"PG"},{"active":0,"id":130,"name":"Paraguay","code":"PY"},{"active":0,"id":45,"name":"Peru","code":"PE"},{"active":0,"id":12,"name":"Philippines","code":"PH"},{"active":0,"id":1,"name":"Pitcairn","code":"PN"},{"active":0,"id":37,"name":"Poland","code":"PL"},{"active":0,"id":27,"name":"Portugal","code":"PT"},{"active":0,"id":101,"name":"Puerto Rico","code":"PR"},{"active":0,"id":1,"name":"Qatar","code":"QA"},{"active":0,"id":135,"name":"R\u00e9union","code":"RE"},{"active":0,"id":30,"name":"Romania","code":"RO"},{"active":0,"id":0,"name":"Russian Federation","code":"RU"},{"active":0,"id":106,"name":"Rwanda","code":"RW"},{"active":0,"id":1,"name":"Saint Barth\u00e9lemy","code":"BL"},{"active":0,"id":1,"name":"\"Saint Helena","code":" Ascension and Tristan da Cunha\""},{"active":0,"id":1,"name":"Saint Kitts and Nevis","code":"KN"},{"active":0,"id":1,"name":"Saint Lucia","code":"LC"},{"active":0,"id":1,"name":"Saint Martin (French part)","code":"MF"},{"active":0,"id":1,"name":"Saint Pierre and Miquelon","code":"PM"},{"active":0,"id":1,"name":"Saint Vincent and the Grenadines","code":"VC"},{"active":0,"id":1,"name":"Samoa","code":"WS"},{"active":0,"id":1,"name":"San Marino","code":"SM"},{"active":0,"id":1,"name":"Sao Tome and Principe","code":"ST"},{"active":0,"id":89,"name":"Saudi Arabia","code":"SA"},{"active":0,"id":63,"name":"Senegal","code":"SN"},{"active":0,"id":105,"name":"Serbia","code":"RS"},{"active":0,"id":1,"name":"Seychelles","code":"SC"},{"active":0,"id":65,"name":"Sierra Leone","code":"SL"},{"active":0,"id":1,"name":"Singapore","code":"SG"},{"active":0,"id":1,"name":"Sint Maarten (Dutch part)","code":"SX"},{"active":0,"id":1,"name":"Slovakia","code":"SK"},{"active":0,"id":7,"name":"Slovenia","code":"SI"},{"active":0,"id":1,"name":"Solomon Islands","code":"SB"},{"active":0,"id":94,"name":"Somalia","code":"SO"},{"active":0,"id":29,"name":"South Africa","code":"ZA"},{"active":0,"id":1,"name":"South Georgia and the South Sandwich Islands","code":"GS"},{"active":0,"id":111,"name":"South Sudan","code":"SS"},{"active":0,"id":24,"name":"Spain","code":"ES"},{"active":0,"id":99,"name":"Sri Lanka","code":"LK"},{"active":0,"id":74,"name":"Sudan","code":"SD"},{"active":0,"id":1,"name":"Suriname","code":"SR"},{"active":0,"id":1,"name":"Svalbard and Jan Mayen","code":"SJ"},{"active":0,"id":132,"name":"Swaziland","code":"SZ"},{"active":0,"id":21,"name":"Sweden","code":"SE"},{"active":0,"id":20,"name":"Switzerland","code":"CH"},{"active":0,"id":90,"name":"Syrian Arab Republic","code":"SY"},{"active":0,"id":1,"name":"\"Taiwan","code":" Province of China\""},{"active":0,"id":48,"name":"Tajikistan","code":"TJ"},{"active":0,"id":1,"name":"\"Tanzania","code":" United Republic of\""},{"active":0,"id":124,"name":"Thailand","code":"TH"},{"active":0,"id":148,"name":"Timor-Leste","code":"TL"},{"active":0,"id":1,"name":"Togo","code":"TG"},{"active":0,"id":1,"name":"Tokelau","code":"TK"},{"active":0,"id":1,"name":"Tonga","code":"TO"},{"active":0,"id":1,"name":"Trinidad and Tobago","code":"TT"},{"active":0,"id":54,"name":"Tunisia","code":"TN"},{"active":0,"id":32,"name":"Turkey","code":"TR"},{"active":0,"id":133,"name":"Turkmenistan","code":"TM"},{"active":0,"id":1,"name":"Turks and Caicos Islands","code":"TC"},{"active":0,"id":1,"name":"Tuvalu","code":"TV"},{"active":0,"id":1,"name":"Uganda","code":"UG"},{"active":0,"id":34,"name":"Ukraine","code":"UA"},{"active":0,"id":87,"name":"United Arab Emirates","code":"AE"},{"active":0,"id":2,"name":"United Kingdom of Great Britain and Northern Ireland","code":"GB"},{"active":0,"id":6,"name":"United States of America","code":"US"},{"active":0,"id":1,"name":"United States Minor Outlying Islands","code":"UM"},{"active":0,"id":1,"name":"Uruguay","code":"UY"},{"active":0,"id":47,"name":"Uzbekistan","code":"UZ"},{"active":0,"id":113,"name":"Vanuatu","code":"VU"},{"active":0,"id":112,"name":"Venezuela (Bolivarian Republic of)","code":"VE"},{"active":0,"id":109,"name":"Viet Nam","code":"VN"},{"active":0,"id":1,"name":"Virgin Islands (British)","code":"VG"},{"active":0,"id":1,"name":"Virgin Islands (U.S.)","code":"VI"},{"active":0,"id":1,"name":"Wallis and Futuna","code":"WF"},{"active":0,"id":1,"name":"Western Sahara","code":"EH"},{"active":0,"id":146,"name":"Yemen","code":"YE"},{"active":0,"id":58,"name":"Zambia","code":"ZM"},{"active":0,"id":142,"name":"Zimbabwe","code":"ZW"},{"active":0,"id":1,"name":"","code":null}]
